krecviz/__init__.py
krecviz/py.typed
krecviz/urdf_logger.py
krecviz/visualize.py
krecviz-0.1.1.dist-info/LICENSE
krecviz-0.1.1.dist-info/METADATA
krecviz-0.1.1.dist-info/WHEEL
krecviz-0.1.1.dist-info/top_level.txt
krecviz-0.1.1.dist-info/RECORD
