Metadata-Version: 2.1
Name: krecviz
Version: 0.1.1
Summary: Visualisation utilities for krec files
Home-page: https://github.com/kscalelabs/krecviz
Author: alik-git
Requires-Python: >=3.11
License-File: LICENSE
Requires-Dist: krec
Requires-Dist: numpy
Requires-Dist: scipy
Requires-Dist: scipy-stubs
Requires-Dist: Pillow
Requires-Dist: types-Pillow
Requires-Dist: rerun-sdk
Requires-Dist: tqdm
Requires-Dist: types-tqdm
Requires-Dist: trimesh
Requires-Dist: urdf_parser_py
Provides-Extra: dev
Requires-Dist: black; extra == "dev"
Requires-Dist: darglint; extra == "dev"
Requires-Dist: mypy; extra == "dev"
Requires-Dist: pytest; extra == "dev"
Requires-Dist: ruff; extra == "dev"
